libABCD/__init__.py
libabcd-2.1.0.dist-info/METADATA
libabcd-2.1.0.dist-info/WHEEL
libabcd-2.1.0.dist-info/licenses/LICENSE
libabcd-2.1.0.dist-info/RECORD
