Metadata-Version: 2.3
Name: libABCD
Version: 2.1.0
Summary: the Autonomous Bariloche Central DAQ, a centralized DAQ system for scientific experiments
Project-URL: Source code, https://gitlab.com/bertou/libabcd
Author-email: Xavier Bertou <bertou@cab.cnea.gov.ar>, Nicolás Avalos <nicolas.avalos@ib.edu.ar>
License-Expression: MIT
License-File: LICENSE
Keywords: logging,mqtt
Classifier: License :: OSI Approved :: MIT License
Classifier: Operating System :: OS Independent
Classifier: Programming Language :: Python :: 3
Classifier: Topic :: Communications
Classifier: Topic :: Scientific/Engineering
Requires-Python: >=3.8
Requires-Dist: paho-mqtt<2
